zpui_lib/__init__.py
zpui_lib/hacks.py
zpui_lib/pytest.ini
zpui_lib/test.sh
zpui_lib/test_commandline
zpui_lib/actions/__init__.py
zpui_lib/actions/actions.py
zpui_lib/apps/__init__.py
zpui_lib/apps/zero_app.py
zpui_lib/helpers/__init__.py
zpui_lib/helpers/config_parse.py
zpui_lib/helpers/env.py
zpui_lib/helpers/general.py
zpui_lib/helpers/input_system.py
zpui_lib/helpers/logger.py
zpui_lib/helpers/pidcheck.py
zpui_lib/helpers/process.py
zpui_lib/helpers/runners.py
zpui_lib/helpers/usability.py
zpui_lib/libs/__init__.py
zpui_lib/libs/dkms_debug.py
zpui_lib/libs/dmesg.py
zpui_lib/libs/if_info.py
zpui_lib/libs/lsusb.py
zpui_lib/libs/systemctl.py
zpui_lib/libs/bugreport/__init__.py
zpui_lib/libs/bugreport/bugreport.py
zpui_lib/libs/bugreport/test_bugreport.py
zpui_lib/libs/bugreport/resources/test.txt
zpui_lib/libs/hw/__init__.py
zpui_lib/libs/hw/smbus_eeprom.py
zpui_lib/libs/linux/__init__.py
zpui_lib/libs/linux/passwd.py
zpui_lib/libs/linux/wpa_cli.py
zpui_lib/libs/linux/wpa_monitor.py
zpui_lib/libs/matrix_client/.gitignore
zpui_lib/libs/matrix_client/.travis.yml
zpui_lib/libs/matrix_client/CONTRIBUTING.rst
zpui_lib/libs/matrix_client/E2E_overview.rst
zpui_lib/libs/matrix_client/LICENSE
zpui_lib/libs/matrix_client/MANIFEST.in
zpui_lib/libs/matrix_client/README.rst
zpui_lib/libs/matrix_client/__init__.py
zpui_lib/libs/matrix_client/setup.cfg
zpui_lib/libs/matrix_client/setup.py
zpui_lib/libs/matrix_client/tox.ini
zpui_lib/libs/matrix_client/docs/Makefile
zpui_lib/libs/matrix_client/docs/source/conf.py
zpui_lib/libs/matrix_client/docs/source/index.rst
zpui_lib/libs/matrix_client/docs/source/matrix_client.rst
zpui_lib/libs/matrix_client/matrix_client/__init__.py
zpui_lib/libs/matrix_client/matrix_client/api.py
zpui_lib/libs/matrix_client/matrix_client/checks.py
zpui_lib/libs/matrix_client/matrix_client/client.py
zpui_lib/libs/matrix_client/matrix_client/device.py
zpui_lib/libs/matrix_client/matrix_client/errors.py
zpui_lib/libs/matrix_client/matrix_client/room.py
zpui_lib-1.3.3.7.dist-info/METADATA
zpui_lib-1.3.3.7.dist-info/WHEEL
zpui_lib-1.3.3.7.dist-info/licenses/LICENSE
zpui_lib-1.3.3.7.dist-info/RECORD
