Metadata-Version: 2.4
Name: zpui-lib
Version: 1.3.3.7
Summary: ZPUI libraries
Project-URL: Homepage, https://github.com/ZeroPhone/ZPUI
Project-URL: Issues, https://github.com/ZeroPhone/ZPUI/issues
Author-email: "Arya (CRImier)" <arya.voronova@gmail.com>
License-File: LICENSE
Classifier: License :: OSI Approved :: GNU Lesser General Public License v3 or later (LGPLv3+)
Classifier: Operating System :: POSIX :: Linux
Classifier: Programming Language :: Python :: 3
Requires-Python: >=3.8
